wisent_parser-1.0.2.dist-info/licenses/AUTHORS
wisent_parser-1.0.2.dist-info/licenses/COPYING
wisent_pkg/__init__.py
wisent_pkg/automaton.py
wisent_pkg/grammar.py
wisent_pkg/helpers.py
wisent_pkg/parser.py
wisent_pkg/scanner.py
wisent_pkg/template.py
wisent_pkg/text.py
wisent_pkg/version.py
wisent_pkg/wisent.py
wisent_parser-1.0.2.dist-info/METADATA
wisent_parser-1.0.2.dist-info/WHEEL
wisent_parser-1.0.2.dist-info/entry_points.txt
wisent_parser-1.0.2.dist-info/top_level.txt
wisent_parser-1.0.2.dist-info/RECORD
