Metadata-Version: 2.4
Name: wisent-parser
Version: 1.0.2
Summary: LR(1) parser generator for Python
Author-email: Jochen Voss <voss@seehuhn.de>
License-Expression: GPL-2.0-or-later
Project-URL: Homepage, http://seehuhn.de/pages/wisent
Project-URL: Bug Reports, https://github.com/seehuhn/wisent/issues
Project-URL: Source, https://github.com/seehuhn/wisent
Keywords: parser,generator,lr1,lalr,compiler
Classifier: Development Status :: 5 - Production/Stable
Classifier: Intended Audience :: Developers
Classifier: Operating System :: OS Independent
Classifier: Programming Language :: Python :: 3
Classifier: Programming Language :: Python :: 3.6
Classifier: Programming Language :: Python :: 3.7
Classifier: Programming Language :: Python :: 3.8
Classifier: Programming Language :: Python :: 3.9
Classifier: Programming Language :: Python :: 3.10
Classifier: Programming Language :: Python :: 3.11
Classifier: Programming Language :: Python :: 3.12
Classifier: Topic :: Software Development :: Code Generators
Classifier: Topic :: Software Development :: Compilers
Requires-Python: >=3.6
License-File: COPYING
License-File: AUTHORS
Dynamic: license-file
